README.txt
setup.py
mogilefs_storage/__init__.py
mogilefs_storage/storage.py
mogilefs_storage.egg-info/PKG-INFO
mogilefs_storage.egg-info/SOURCES.txt
mogilefs_storage.egg-info/dependency_links.txt
mogilefs_storage.egg-info/requires.txt
mogilefs_storage.egg-info/top_level.txt
mogilefs_storage.egg-info/zip-safe