Metadata-Version: 1.0
Name: mogilefs-storage
Version: 0.2
Summary: MogileFS FileStorage for Django
Home-page: UNKNOWN
Author: Daniel E. Bruce
Author-email: ircubic@gmail.com
License: MIT
Platform: UNKNOWN
Classifier: Development Status :: 3 - Alpha
Classifier: Framework :: Django
Classifier: License :: OSI Approved :: MIT License
